xia_pypi/__init__.py
xia_pypi/example.py
xia_pypi-0.0.2.dist-info/LICENSE
xia_pypi-0.0.2.dist-info/METADATA
xia_pypi-0.0.2.dist-info/WHEEL
xia_pypi-0.0.2.dist-info/top_level.txt
xia_pypi-0.0.2.dist-info/RECORD
